mthree/__init__.py
mthree/_helpers.py
mthree/circuits.py
mthree/classes.py
mthree/converters.cpp
mthree/converters.cpython-311-x86_64-linux-gnu.so
mthree/converters.pxd
mthree/converters.pyx
mthree/direct.py
mthree/exceptions.py
mthree/expval.cpp
mthree/expval.cpython-311-x86_64-linux-gnu.so
mthree/expval.pyx
mthree/hamming.cpp
mthree/hamming.cpython-311-x86_64-linux-gnu.so
mthree/hamming.pyx
mthree/iterative.py
mthree/matrix.cpp
mthree/matrix.cpython-311-x86_64-linux-gnu.so
mthree/matrix.pyx
mthree/matvec.cpp
mthree/matvec.cpython-311-x86_64-linux-gnu.so
mthree/matvec.pyx
mthree/mitigation.py
mthree/norms.py
mthree/probability.cpp
mthree/probability.cpython-311-x86_64-linux-gnu.so
mthree/probability.pyx
mthree/utils.py
mthree/version.py
mthree/generators/__init__.py
mthree/generators/hadamard.cpp
mthree/generators/hadamard.cpython-311-x86_64-linux-gnu.so
mthree/generators/hadamard.pyx
mthree/src/col_renorm.h
mthree/src/distance.h
mthree/src/elements.h
mthree/src/matvec.h
mthree/test/__init__.py
mthree/test/column_testing.cpp
mthree/test/column_testing.cpython-311-x86_64-linux-gnu.so
mthree/test/column_testing.pyx
mthree/test/converters_testing.cpp
mthree/test/converters_testing.cpython-311-x86_64-linux-gnu.so
mthree/test/converters_testing.pyx
mthree/test/test_collections.py
mthree/test/test_columns.py
mthree/test/test_converters.py
mthree/test/test_default_shots.py
mthree/test/test_details.py
mthree/test/test_dynamic.py
mthree/test/test_expvals.py
mthree/test/test_extra_cals.py
mthree/test/test_faulty.py
mthree/test/test_file_io.py
mthree/test/test_full.py
mthree/test/test_generators.py
mthree/test/test_grouping.py
mthree/test/test_hamming.py
mthree/test/test_inoperable_qubits.py
mthree/test/test_list_inputs.py
mthree/test/test_marginals.py
mthree/test/test_matvec.py
mthree/test/test_meas_mapping.py
mthree/test/test_methods.py
mthree/test/test_multi_job.py
mthree/test/test_odd_cases.py
mthree-3.0.0.dist-info/METADATA
mthree-3.0.0.dist-info/WHEEL
mthree-3.0.0.dist-info/top_level.txt
mthree-3.0.0.dist-info/RECORD
mthree-3.0.0.dist-info/licenses/LICENSE.txt
