Metadata-Version: 2.4
Name: mthree
Version: 3.0.0
Summary: M3: Matrix-free measurement mitigation
Home-page: 
Author: Paul Nation
Author-email: paul.nation@ibm.com
License: Apache 2.0
Classifier: License :: OSI Approved :: Apache Software License
Classifier: Intended Audience :: Developers
Classifier: Intended Audience :: Science/Research
Classifier: Operating System :: Microsoft :: Windows
Classifier: Operating System :: MacOS
Classifier: Operating System :: POSIX :: Linux
Classifier: Programming Language :: Python :: 3.9
Classifier: Programming Language :: Python :: 3.10
Classifier: Programming Language :: Python :: 3.11
Classifier: Programming Language :: Python :: 3.12
Classifier: Topic :: Scientific/Engineering
Requires-Python: >=3.9
License-File: LICENSE.txt
Requires-Dist: numpy>=1.23
Requires-Dist: scipy>=1.11.1
Requires-Dist: cython>=3.0.10
Requires-Dist: qiskit>=1.0
Requires-Dist: psutil
Requires-Dist: orjson>=3.0.0
Requires-Dist: runningman>=2.1
Dynamic: author
Dynamic: author-email
Dynamic: classifier
Dynamic: description
Dynamic: description-content-type
Dynamic: license
Dynamic: license-file
Dynamic: requires-dist
Dynamic: requires-python
Dynamic: summary
